setup.cfg
setup.py
Quiz_library.egg-info/PKG-INFO
Quiz_library.egg-info/SOURCES.txt
Quiz_library.egg-info/dependency_links.txt
Quiz_library.egg-info/top_level.txt
quiz/__init__.py
quiz/quiz.py