Metadata-Version: 2.4
Name: Quiz_library
Version: 1.0
Summary: Library untuk kuis
Author: Satria Ramadhan
Author-email: ram@telkomuniversity.ac.id
Dynamic: author
Dynamic: author-email
Dynamic: summary
